bfscplate2d/__init__.py
bfscplate2d/bfscplate2d.cpython-311-darwin.so
bfscplate2d/bfscplate2d.pyx
bfscplate2d/quadrature.py
bfscplate2d/version.py
bfscplate2d-0.3.1.data/data/LICENSE
bfscplate2d-0.3.1.data/data/README.md
bfscplate2d-0.3.1.dist-info/LICENSE
bfscplate2d-0.3.1.dist-info/METADATA
bfscplate2d-0.3.1.dist-info/WHEEL
bfscplate2d-0.3.1.dist-info/top_level.txt
bfscplate2d-0.3.1.dist-info/RECORD
